odoo/addons/edi_endpoint_oca/README.rst
odoo/addons/edi_endpoint_oca/__init__.py
odoo/addons/edi_endpoint_oca/__manifest__.py
odoo/addons/edi_endpoint_oca/data/server_action.xml
odoo/addons/edi_endpoint_oca/demo/edi_backend_demo.xml
odoo/addons/edi_endpoint_oca/i18n/edi_endpoint_oca.pot
odoo/addons/edi_endpoint_oca/i18n/es.po
odoo/addons/edi_endpoint_oca/i18n/it.po
odoo/addons/edi_endpoint_oca/migrations/14.0.1.4.0/post-migrate.py
odoo/addons/edi_endpoint_oca/models/__init__.py
odoo/addons/edi_endpoint_oca/models/edi_backend.py
odoo/addons/edi_endpoint_oca/models/edi_backend_type.py
odoo/addons/edi_endpoint_oca/models/edi_endpoint.py
odoo/addons/edi_endpoint_oca/models/edi_exchange_consumer_mixin.py
odoo/addons/edi_endpoint_oca/models/edi_exchange_record.py
odoo/addons/edi_endpoint_oca/readme/CONFIGURE.rst
odoo/addons/edi_endpoint_oca/readme/CONTRIBUTORS.rst
odoo/addons/edi_endpoint_oca/readme/DESCRIPTION.rst
odoo/addons/edi_endpoint_oca/security/ir.model.access.csv
odoo/addons/edi_endpoint_oca/static/description/icon.png
odoo/addons/edi_endpoint_oca/static/description/index.html
odoo/addons/edi_endpoint_oca/tests/__init__.py
odoo/addons/edi_endpoint_oca/tests/test_edi_endpoint.py
odoo/addons/edi_endpoint_oca/tests/test_edi_endpoint_controller.py
odoo/addons/edi_endpoint_oca/views/edi_backend_views.xml
odoo/addons/edi_endpoint_oca/views/edi_endpoint_views.xml
odoo/addons/edi_endpoint_oca/views/edi_exchange_record_views.xml
odoo14_addon_edi_endpoint_oca-14.0.1.5.2.dist-info/METADATA
odoo14_addon_edi_endpoint_oca-14.0.1.5.2.dist-info/WHEEL
odoo14_addon_edi_endpoint_oca-14.0.1.5.2.dist-info/top_level.txt
odoo14_addon_edi_endpoint_oca-14.0.1.5.2.dist-info/RECORD
