Metadata-Version: 2.1
Name: odoo14-addon-edi_endpoint_oca
Version: 14.0.1.5.2
Summary: Base module allowing configuration of custom endpoints for EDI framework.
Home-page: https://github.com/OCA/edi
Author: Camptocamp,Odoo Community Association (OCA)
Author-email: support@odoo-community.org
License: LGPL-3
Classifier: Programming Language :: Python
Classifier: Framework :: Odoo
Classifier: Framework :: Odoo :: 14.0
Classifier: License :: OSI Approved :: GNU Lesser General Public License v3 (LGPLv3)
Classifier: Development Status :: 4 - Beta
Requires-Python: >=3.6
Requires-Dist: odoo14-addon-base-edi
Requires-Dist: odoo14-addon-edi-oca
Requires-Dist: odoo14-addon-endpoint
Requires-Dist: odoo<14.1dev,>=14.0a
